package1/__init__.py
package2/__init__.py
package3/__init__.py
MyPackage_385-0.0.0.dist-info/METADATA
MyPackage_385-0.0.0.dist-info/WHEEL
MyPackage_385-0.0.0.dist-info/top_level.txt
MyPackage_385-0.0.0.dist-info/RECORD
